KNICS_Jupyter_frontend/__init__.py
KNICS_Jupyter_frontend/_version.py
KNICS_Jupyter_frontend/labextension/build_log.json
KNICS_Jupyter_frontend/labextension/install.json
KNICS_Jupyter_frontend/labextension/package.json
KNICS_Jupyter_frontend/labextension/static/lib_index_js.dd61c965c457f092bd9a.js
KNICS_Jupyter_frontend/labextension/static/lib_index_js.dd61c965c457f092bd9a.js.map
KNICS_Jupyter_frontend/labextension/static/remoteEntry.a910049d2e28ec9b8a93.js
KNICS_Jupyter_frontend/labextension/static/remoteEntry.a910049d2e28ec9b8a93.js.map
KNICS_Jupyter_frontend/labextension/static/style.js
KNICS_Jupyter_frontend/labextension/static/style_index_js.2b67ef2180e84a104942.js
KNICS_Jupyter_frontend/labextension/static/style_index_js.2b67ef2180e84a104942.js.map
KNICS_Jupyter_frontend/labextension/static/vendors-node_modules_css-loader_dist_runtime_api_js-node_modules_css-loader_dist_runtime_cssW-72eba1.416973763e56b24852f8.js
KNICS_Jupyter_frontend/labextension/static/vendors-node_modules_css-loader_dist_runtime_api_js-node_modules_css-loader_dist_runtime_cssW-72eba1.416973763e56b24852f8.js.map
knics_jupyter_frontend-0.1.0.data/data/share/jupyter/labextensions/KNICS_Jupyter_frontend/build_log.json
knics_jupyter_frontend-0.1.0.data/data/share/jupyter/labextensions/KNICS_Jupyter_frontend/install.json
knics_jupyter_frontend-0.1.0.data/data/share/jupyter/labextensions/KNICS_Jupyter_frontend/package.json
knics_jupyter_frontend-0.1.0.data/data/share/jupyter/labextensions/KNICS_Jupyter_frontend/static/lib_index_js.dd61c965c457f092bd9a.js
knics_jupyter_frontend-0.1.0.data/data/share/jupyter/labextensions/KNICS_Jupyter_frontend/static/lib_index_js.dd61c965c457f092bd9a.js.map
knics_jupyter_frontend-0.1.0.data/data/share/jupyter/labextensions/KNICS_Jupyter_frontend/static/remoteEntry.a910049d2e28ec9b8a93.js
knics_jupyter_frontend-0.1.0.data/data/share/jupyter/labextensions/KNICS_Jupyter_frontend/static/remoteEntry.a910049d2e28ec9b8a93.js.map
knics_jupyter_frontend-0.1.0.dist-info/METADATA
knics_jupyter_frontend-0.1.0.dist-info/WHEEL
knics_jupyter_frontend-0.1.0.dist-info/licenses/LICENSE
knics_jupyter_frontend-0.1.0.dist-info/RECORD
