Metadata-Version: 2.1
Name: KNICS_Jupyter_frontend
Version: 0.1.0
Summary: A JupyterLab extension.
Project-URL: Homepage, https://github.com/ICTLearningSciences/KNICS_Jupyter_frontend
Project-URL: Bug Tracker, https://github.com/ICTLearningSciences/KNICS_Jupyter_frontend/issues
Project-URL: Repository, https://github.com/ICTLearningSciences/KNICS_Jupyter_frontend.git
Author-email: Daniel Auerbach <auerbach@ict.usc.edu>
License: BSD 3-Clause License
License-File: LICENSE
Classifier: Framework :: Jupyter
Classifier: Framework :: Jupyter :: JupyterLab
Classifier: Framework :: Jupyter :: JupyterLab :: 3
Classifier: Framework :: Jupyter :: JupyterLab :: Extensions
Classifier: Framework :: Jupyter :: JupyterLab :: Extensions :: Prebuilt
Classifier: License :: OSI Approved :: BSD License
Classifier: Programming Language :: Python
Classifier: Programming Language :: Python :: 3
Classifier: Programming Language :: Python :: 3.7
Classifier: Programming Language :: Python :: 3.8
Classifier: Programming Language :: Python :: 3.9
Classifier: Programming Language :: Python :: 3.10
Requires-Python: >=3.7
Provides-Extra: test
Requires-Dist: coverage; extra == 'test'
Requires-Dist: pytest; extra == 'test'
Requires-Dist: pytest-asyncio; extra == 'test'
Requires-Dist: pytest-cov; extra == 'test'
Requires-Dist: pytest-tornasync; extra == 'test'
